.DS_Store
pyroglancer/__init__.py
pyroglancer/__version__.py
pyroglancer/createconfig.py
pyroglancer/debug.py
pyroglancer/flywire.py
pyroglancer/layers.py
pyroglancer/loadconfig.py
pyroglancer/localserver.py
pyroglancer/meshgenerator.py
pyroglancer/ngspaces.py
pyroglancer/ngviewer.py
pyroglancer/points.py
pyroglancer/skeletons.py
pyroglancer/synapses.py
pyroglancer/utils.py
pyroglancer/volumes.py
pyroglancer/tests/__init__.py
pyroglancer/tests/conftest.py
pyroglancer/tests/test_layers.py
pyroglancer/tests/test_localserver.py
pyroglancer/tests/test_ngspaces.py
pyroglancer/tests/test_ngviewer.py
pyroglancer/tests/test_points.py
pyroglancer/tests/test_skeletons.py
pyroglancer/tests/test_synapses.py
pyroglancer/tests/test_utils.py
pyroglancer/tests/test_volumes.py
pyroglancer-0.0.4.dist-info/LICENSE
pyroglancer-0.0.4.dist-info/METADATA
pyroglancer-0.0.4.dist-info/WHEEL
pyroglancer-0.0.4.dist-info/entry_points.txt
pyroglancer-0.0.4.dist-info/top_level.txt
pyroglancer-0.0.4.dist-info/RECORD
