Metadata-Version: 2.1
Name: pyroglancer
Version: 0.0.4
Summary: Pythonic interface to neuroglancer for displaying neuronal and synaptic data
Home-page: https://github.com/SridharJagannathan/pyroglancer
Author: Sridhar Jagannathan
Author-email: j.sridharrajan@gmail.com
License: BSD (3-clause)
Platform: UNKNOWN
Classifier: Development Status :: 2 - Pre-Alpha
Classifier: Natural Language :: English
Classifier: Intended Audience :: Science/Research
Classifier: Topic :: Scientific/Engineering :: Bio-Informatics
Classifier: Programming Language :: Python :: 3
Classifier: Programming Language :: Python :: 3.6
Classifier: Programming Language :: Python :: 3.7
Classifier: Programming Language :: Python :: 3.8
Classifier: Programming Language :: Python :: 3.9
Requires-Python: >=3.6
Requires-Dist: neuroglancer (>=2.15)
Requires-Dist: python-catmaid (>=2.0.2)
Requires-Dist: navis (>=0.5.1)
Requires-Dist: numpy (>=1.16)
Requires-Dist: json5 (>=0.9.5)
Requires-Dist: cloud-volume
Requires-Dist: webcolors (>=1.3)
Requires-Dist: pyyaml
Requires-Dist: nglui (>=2.4.0)
Requires-Dist: more-itertools
Requires-Dist: open3d
Requires-Dist: scikit-image
